Metadata-Version: 1.0
Name: boostmpi
Version: 1.37.0
Summary: Boost MPI Python wrappers
Home-page: http://mathema.tician.de/software/boostmpi
Author: Andreas Kloeckner
Author-email: inform@tiker.net
License: Boost Software License V1
Platform: UNKNOWN
Classifier: Environment :: Console
Classifier: Development Status :: 4 - Beta
Classifier: Intended Audience :: Developers
Classifier: Intended Audience :: Other Audience
Classifier: Intended Audience :: Science/Research
Classifier: Natural Language :: English
Classifier: Programming Language :: C++
Classifier: Programming Language :: Python
Classifier: Topic :: Software Development :: Libraries
Classifier: Topic :: Scientific/Engineering
